splinedist/__init__.py
splinedist/big.py
splinedist/matching.py
splinedist/nms.py
splinedist/sample_patches.py
splinedist/splinegenerator.py
splinedist/utils.py
splinedist/version.py
splinedist/geometry/__init__.py
splinedist/geometry/geom2d.py
splinedist/models/__init__.py
splinedist/models/base.py
splinedist/models/model2d.py
splinedist/plot/__init__.py
splinedist/plot/plot.py
splinedist/plot/render.py
splinedist-0.1.2.dist-info/LICENSE
splinedist-0.1.2.dist-info/LICENSE_stardist.txt
splinedist-0.1.2.dist-info/METADATA
splinedist-0.1.2.dist-info/WHEEL
splinedist-0.1.2.dist-info/top_level.txt
splinedist-0.1.2.dist-info/RECORD
