Metadata-Version: 2.1
Name: splinedist
Version: 0.1.2
Summary: splinedist
Home-page: https://github.com/uhlmanngroup/splinedist
Author: uhlmanngroup
Author-email: uhlmann@ebi.ac.uk
Keywords: splinedist
Classifier: Intended Audience :: Developers
Classifier: Natural Language :: English
Classifier: Programming Language :: Python :: 3.8
Classifier: Programming Language :: Python :: 3.9
Classifier: Programming Language :: Python :: 3.10
License-File: LICENSE
License-File: LICENSE_stardist.txt
Requires-Dist: stardist (>=0.8.3)
Requires-Dist: tensorflow
Requires-Dist: opencv-python-headless
Requires-Dist: csbdeep (>=0.6.3)
